flake8_typing_as_t.py
flake8_typing_as_t-1.0.0.dist-info/entry_points.txt
flake8_typing_as_t-1.0.0.dist-info/LICENSE.txt
flake8_typing_as_t-1.0.0.dist-info/WHEEL
flake8_typing_as_t-1.0.0.dist-info/METADATA
flake8_typing_as_t-1.0.0.dist-info/RECORD
