Metadata-Version: 2.3
Name: flake8-typing-as-t
Version: 1.0.0
Summary: A flake8 plugin to check typing import style
Keywords: 
Author-email: Stephen Rosen <sirosen0@gmail.com>
Requires-Python: >=3.7
Classifier: Development Status :: 5 - Production/Stable
Classifier: Programming Language :: Python
Classifier: Programming Language :: Python :: Implementation :: CPython
Classifier: Programming Language :: Python :: Implementation :: PyPy
Project-URL: source, https://github.com/sirosen/flake8-typing-as-t
